README.md
setup.py
easytrans/LICENSE
easytrans/README.md
easytrans/__init__.py
easytrans/constant.py
easytrans/data_to_db.py
easytrans/data_to_file.py
easytrans/file_to_data.py
easytrans/file_to_doc.py
easytrans/file_to_pdf.py
easytrans/file_to_png.py
easytrans/img_to_img.py
easytrans/utils.py
easytrans.egg-info/PKG-INFO
easytrans.egg-info/SOURCES.txt
easytrans.egg-info/dependency_links.txt
easytrans.egg-info/requires.txt
easytrans.egg-info/top_level.txt