Metadata-Version: 2.1
Name: easytrans
Version: 0.0.7
Summary: The easytrans makes the file transfer simpler!
Home-page: https://github.com/YouAreOnlyOne
Author: Frank YCJ
Author-email: 1320259466@qq.com
License: Apache 2.0 license
Project-URL: Bug Tracker, https://github.com/YouAreOnlyOne/FastFrameJar/issues
Project-URL: Documentation, https://github.com/YouAreOnlyOne/FastFrameJar
Project-URL: Source Code, https://github.com/YouAreOnlyOne/FastFrameJar
Keywords: file format transfer word doc pdf png jpg txt convert
Platform: UNKNOWN
Classifier: Programming Language :: Python
Classifier: License :: OSI Approved :: MIT License
Classifier: Operating System :: OS Independent
